parse2docs/__init__.py
parse2docs/app.py
parse2docs/argfinder.py
parse2docs/markdown_renderer.py
parse2docs/module_loader.py
parse2docs-0.1.3.dist-info/LICENSE
parse2docs-0.1.3.dist-info/METADATA
parse2docs-0.1.3.dist-info/WHEEL
parse2docs-0.1.3.dist-info/entry_points.txt
parse2docs-0.1.3.dist-info/RECORD
