Metadata-Version: 2.1
Name: parse2docs
Version: 0.1.3
Summary: Generate usage documentation from Python scripts using the `argparse` module
License: MIT
Author: Fernando Cordeiro
Requires-Python: >=3.11,<4.0
Classifier: License :: OSI Approved :: MIT License
Classifier: Programming Language :: Python :: 3
Classifier: Programming Language :: Python :: 3.11
